llmadventure/__init__.py
llmadventure/plugins.py
llmadventure/cli/__init__.py
llmadventure/cli/display.py
llmadventure/cli/menus.py
llmadventure/core/__init__.py
llmadventure/core/combat.py
llmadventure/core/creature.py
llmadventure/core/evolution.py
llmadventure/core/game.py
llmadventure/core/inventory.py
llmadventure/core/player.py
llmadventure/core/quest.py
llmadventure/core/world.py
llmadventure/engine/__init__.py
llmadventure/engine/llm_interface.py
llmadventure/engine/memory.py
llmadventure/engine/procedural_gen.py
llmadventure/engine/prompt_templates.py
llmadventure/utils/__init__.py
llmadventure/utils/config.py
llmadventure/utils/file_ops.py
llmadventure/utils/logger.py
llmadventure/web/__init__.py
llmadventure-1.0.4.dist-info/METADATA
llmadventure-1.0.4.dist-info/WHEEL
llmadventure-1.0.4.dist-info/entry_points.txt
llmadventure-1.0.4.dist-info/top_level.txt
llmadventure-1.0.4.dist-info/RECORD
