Metadata-Version: 2.4
Name: llmadventure
Version: 1.0.4
Summary: 🎮 AI-Powered CLI Text Adventure Game - Create infinite stories with LLM
Author-email: SoftwareApkDev <softwareapkdev2022@gmail.com>
Maintainer-email: SoftwareApkDev <softwareapkdev2022@gmail.com>
License: MIT
Project-URL: Repository, https://github.com/SoftwareApkDev/llmadventure
Keywords: ai,game,adventure,cli,text-adventure,gemini,llm,rpg,storytelling,procedural-generation,interactive-fiction,terminal-game,ai-gaming,machine-learning,natural-language
Classifier: Development Status :: 5 - Production/Stable
Classifier: Intended Audience :: End Users/Desktop
Classifier: Intended Audience :: Developers
Classifier: Intended Audience :: Education
Classifier: License :: OSI Approved :: MIT License
Classifier: Programming Language :: Python :: 3
Classifier: Programming Language :: Python :: 3.8
Classifier: Programming Language :: Python :: 3.9
Classifier: Programming Language :: Python :: 3.10
Classifier: Programming Language :: Python :: 3.11
Classifier: Programming Language :: Python :: 3.12
Classifier: Topic :: Games/Entertainment
Classifier: Topic :: Scientific/Engineering :: Artificial Intelligence
Classifier: Topic :: Software Development :: Libraries :: Python Modules
Classifier: Topic :: Text Processing :: Linguistic
Classifier: Topic :: Education
Classifier: Topic :: Multimedia :: Graphics :: Presentation
Classifier: Topic :: System :: Systems Administration
Classifier: Topic :: Terminals
Classifier: Topic :: Utilities
Classifier: Operating System :: OS Independent
Classifier: Environment :: Console
Classifier: Framework :: Pytest
Classifier: Typing :: Typed
Requires-Python: >=3.8
Requires-Dist: google-generativeai>=0.3.0
Requires-Dist: rich>=13.0.0
Requires-Dist: click>=8.0.0
Requires-Dist: pydantic>=2.0.0
Requires-Dist: typer>=0.9.0
Requires-Dist: colorama>=0.4.6
Requires-Dist: pyyaml>=6.0
Requires-Dist: python-dotenv>=1.0.0
Requires-Dist: aiofiles>=23.0.0
Requires-Dist: asyncio-mqtt>=0.16.0
Requires-Dist: websockets>=11.0.0
Requires-Dist: fastapi>=0.104.0
Requires-Dist: uvicorn>=0.24.0
Requires-Dist: jinja2>=3.1.0
Requires-Dist: markdown>=3.5.0
Requires-Dist: pillow>=10.0.0
Requires-Dist: matplotlib>=3.7.0
Requires-Dist: plotly>=5.17.0
Requires-Dist: pandas>=2.0.0
Requires-Dist: numpy>=1.24.0
Provides-Extra: dev
Requires-Dist: pytest>=7.0.0; extra == "dev"
Requires-Dist: pytest-cov>=4.0.0; extra == "dev"
Requires-Dist: pytest-asyncio>=0.21.0; extra == "dev"
Requires-Dist: black>=23.0.0; extra == "dev"
Requires-Dist: isort>=5.12.0; extra == "dev"
Requires-Dist: flake8>=6.0.0; extra == "dev"
Requires-Dist: mypy>=1.0.0; extra == "dev"
Requires-Dist: pre-commit>=3.0.0; extra == "dev"
Requires-Dist: tox>=4.0.0; extra == "dev"
Requires-Dist: sphinx>=7.0.0; extra == "dev"
Requires-Dist: sphinx-rtd-theme>=1.3.0; extra == "dev"
Provides-Extra: web
Requires-Dist: fastapi>=0.104.0; extra == "web"
Requires-Dist: uvicorn>=0.24.0; extra == "web"
Requires-Dist: jinja2>=3.1.0; extra == "web"
Requires-Dist: websockets>=11.0.0; extra == "web"
Provides-Extra: ai
Requires-Dist: openai>=1.0.0; extra == "ai"
Requires-Dist: anthropic>=0.7.0; extra == "ai"
Requires-Dist: langchain>=0.1.0; extra == "ai"
Requires-Dist: transformers>=4.35.0; extra == "ai"
Requires-Dist: torch>=2.0.0; extra == "ai"
Provides-Extra: data
Requires-Dist: pandas>=2.0.0; extra == "data"
Requires-Dist: numpy>=1.24.0; extra == "data"
Requires-Dist: matplotlib>=3.7.0; extra == "data"
Requires-Dist: plotly>=5.17.0; extra == "data"
Requires-Dist: seaborn>=0.12.0; extra == "data"
Provides-Extra: full
Requires-Dist: llmadventure[ai,data,dev,web]; extra == "full"
